simplechanges/__init__.py
simplechanges/parser.py
simplechanges-0.1.0.dist-info/LICENSE.txt
simplechanges-0.1.0.dist-info/WHEEL
simplechanges-0.1.0.dist-info/METADATA
simplechanges-0.1.0.dist-info/RECORD
