Metadata-Version: 2.1
Name: simplechanges
Version: 0.1.0
Summary: A simple changelog parser
Home-page: https://github.com/UnscriptedVN/simplechanges
License: MPL-2.0
Author: Marquis Kurt
Author-email: software@marquiskurt.net
Requires-Python: >=2.7, !=3.0.*, !=3.1.*, !=3.2.*, !=3.3.*, !=3.4.*, !=3.5.*
Classifier: License :: OSI Approved
Classifier: Programming Language :: Python :: 2
Classifier: Programming Language :: Python :: 2.7
Classifier: Programming Language :: Python :: 3
Classifier: Programming Language :: Python :: 3.7
Classifier: Programming Language :: Python :: 3.8
Classifier: Topic :: Software Development :: Libraries
Project-URL: Repository, https://github.com/UnscriptedVN/simplechanges
